[ {
  "id" : 9574776881,
  "name" : "Aurora Delete",
  "status" : "completed",
  "conclusion" : "success",
  "event" : "workflow_dispatch",
  "path" : ".github/workflows/aurora-delete.yml",
  "repository" : {
    "full_name" : "keycloak/keycloak"
  },
  "head_branch" : "quarkus-next",
  "created_at" : "2024-06-19T01:43:30Z",
  "run_attempt" : 1
}, {
  "id" : 9574741593,
  "name" : "Aurora Delete",
  "status" : "completed",
  "conclusion" : "success",
  "event" : "workflow_dispatch",
  "path" : ".github/workflows/aurora-delete.yml",
  "repository" : {
    "full_name" : "keycloak/keycloak"
  },
  "head_branch" : "main",
  "created_at" : "2024-06-19T01:39:04Z",
  "run_attempt" : 1
}, {
  "id" : 9574021944,
  "name" : "Weblate Sync",
  "status" : "completed",
  "conclusion" : "success",
  "event" : "schedule",
  "path" : ".github/workflows/weblate.yml",
  "repository" : {
    "full_name" : "keycloak/keycloak"
  },
  "head_branch" : "main",
  "created_at" : "2024-06-19T00:20:40Z",
  "run_attempt" : 1
}, {
  "id" : 9573965421,
  "name" : "Keycloak JavaScript CI",
  "status" : "completed",
  "conclusion" : "success",
  "event" : "workflow_dispatch",
  "path" : ".github/workflows/js-ci.yml",
  "repository" : {
    "full_name" : "keycloak/keycloak"
  },
  "head_branch" : "main",
  "created_at" : "2024-06-19T00:15:10Z",
  "run_attempt" : 1
}, {
  "id" : 9573965318,
  "name" : "Keycloak Operator CI",
  "status" : "completed",
  "conclusion" : "success",
  "event" : "workflow_dispatch",
  "path" : ".github/workflows/operator-ci.yml",
  "repository" : {
    "full_name" : "keycloak/keycloak"
  },
  "head_branch" : "main",
  "created_at" : "2024-06-19T00:15:09Z",
  "run_attempt" : 1
}, {
  "id" : 9573965246,
  "name" : "Trivy",
  "status" : "completed",
  "conclusion" : "success",
  "event" : "workflow_dispatch",
  "path" : ".github/workflows/trivy-analysis.yml",
  "repository" : {
    "full_name" : "keycloak/keycloak"
  },
  "head_branch" : "main",
  "created_at" : "2024-06-19T00:15:09Z",
  "run_attempt" : 1
}, {
  "id" : 9573965125,
  "name" : "Keycloak CI",
  "status" : "completed",
  "conclusion" : "success",
  "event" : "workflow_dispatch",
  "path" : ".github/workflows/ci.yml",
  "repository" : {
    "full_name" : "keycloak/keycloak"
  },
  "head_branch" : "main",
  "created_at" : "2024-06-19T00:15:08Z",
  "run_attempt" : 1
}, {
  "id" : 9573964985,
  "name" : "Snyk",
  "status" : "completed",
  "conclusion" : "success",
  "event" : "workflow_dispatch",
  "path" : ".github/workflows/snyk-analysis.yml",
  "repository" : {
    "full_name" : "keycloak/keycloak"
  },
  "head_branch" : "release/25.0",
  "created_at" : "2024-06-19T00:15:07Z",
  "run_attempt" : 1
}, {
  "id" : 9573964981,
  "name" : "Snyk",
  "status" : "completed",
  "conclusion" : "success",
  "event" : "workflow_dispatch",
  "path" : ".github/workflows/snyk-analysis.yml",
  "repository" : {
    "full_name" : "keycloak/keycloak"
  },
  "head_branch" : "main",
  "created_at" : "2024-06-19T00:15:07Z",
  "run_attempt" : 1
}, {
  "id" : 9573964997,
  "name" : "Keycloak Documentation",
  "status" : "completed",
  "conclusion" : "success",
  "event" : "workflow_dispatch",
  "path" : ".github/workflows/documentation.yml",
  "repository" : {
    "full_name" : "keycloak/keycloak"
  },
  "head_branch" : "main",
  "created_at" : "2024-06-19T00:15:07Z",
  "run_attempt" : 1
}, {
  "id" : 9573961532,
  "name" : "Scheduled nightly workflows",
  "status" : "completed",
  "conclusion" : "success",
  "event" : "schedule",
  "path" : ".github/workflows/schedule-nightly.yml",
  "repository" : {
    "full_name" : "keycloak/keycloak"
  },
  "head_branch" : "main",
  "created_at" : "2024-06-19T00:14:48Z",
  "run_attempt" : 1
}, {
  "id" : 9573922020,
  "name" : "Keycloak Operator CI",
  "status" : "completed",
  "conclusion" : "success",
  "event" : "workflow_dispatch",
  "path" : ".github/workflows/operator-ci.yml",
  "repository" : {
    "full_name" : "keycloak/keycloak"
  },
  "head_branch" : "quarkus-next",
  "created_at" : "2024-06-19T00:10:59Z",
  "run_attempt" : 1
}, {
  "id" : 9573921706,
  "name" : "Keycloak CI",
  "status" : "completed",
  "conclusion" : "failure",
  "event" : "workflow_dispatch",
  "path" : ".github/workflows/ci.yml",
  "repository" : {
    "full_name" : "keycloak/keycloak"
  },
  "head_branch" : "quarkus-next",
  "created_at" : "2024-06-19T00:10:56Z",
  "run_attempt" : 1
}, {
  "id" : 9573903576,
  "name" : "Quarkus Next",
  "status" : "completed",
  "conclusion" : "success",
  "event" : "schedule",
  "path" : ".github/workflows/quarkus-next.yml",
  "repository" : {
    "full_name" : "keycloak/keycloak"
  },
  "head_branch" : "main",
  "created_at" : "2024-06-19T00:09:04Z",
  "run_attempt" : 1
}, {
  "id" : 9568002077,
  "name" : "Aurora Delete",
  "status" : "completed",
  "conclusion" : "success",
  "event" : "workflow_dispatch",
  "path" : ".github/workflows/aurora-delete.yml",
  "repository" : {
    "full_name" : "keycloak/keycloak"
  },
  "head_branch" : "release/24.0",
  "created_at" : "2024-06-18T15:34:44Z",
  "run_attempt" : 1
}, {
  "id" : 9567997972,
  "name" : "Aurora Delete",
  "status" : "completed",
  "conclusion" : "success",
  "event" : "workflow_dispatch",
  "path" : ".github/workflows/aurora-delete.yml",
  "repository" : {
    "full_name" : "keycloak/keycloak"
  },
  "head_branch" : "release/25.0",
  "created_at" : "2024-06-18T15:34:27Z",
  "run_attempt" : 1
}, {
  "id" : 9566044028,
  "name" : "Keycloak Documentation",
  "status" : "completed",
  "conclusion" : "failure",
  "event" : "push",
  "path" : ".github/workflows/documentation.yml",
  "repository" : {
    "full_name" : "keycloak/keycloak"
  },
  "head_branch" : "release/24.0",
  "created_at" : "2024-06-18T13:33:06Z",
  "run_attempt" : 1
}, {
  "id" : 9566044008,
  "name" : "Keycloak JavaScript CI",
  "status" : "completed",
  "conclusion" : "failure",
  "event" : "push",
  "path" : ".github/workflows/js-ci.yml",
  "repository" : {
    "full_name" : "keycloak/keycloak"
  },
  "head_branch" : "release/24.0",
  "created_at" : "2024-06-18T13:33:06Z",
  "run_attempt" : 1
}, {
  "id" : 9566044007,
  "name" : "Keycloak Guides",
  "status" : "completed",
  "conclusion" : "success",
  "event" : "push",
  "path" : ".github/workflows/guides.yml",
  "repository" : {
    "full_name" : "keycloak/keycloak"
  },
  "head_branch" : "release/24.0",
  "created_at" : "2024-06-18T13:33:06Z",
  "run_attempt" : 1
}, {
  "id" : 9566044023,
  "name" : "Keycloak CI",
  "status" : "completed",
  "conclusion" : "success",
  "event" : "push",
  "path" : ".github/workflows/ci.yml",
  "repository" : {
    "full_name" : "keycloak/keycloak"
  },
  "head_branch" : "release/24.0",
  "created_at" : "2024-06-18T13:33:06Z",
  "run_attempt" : 1
}, {
  "id" : 9566044006,
  "name" : "Keycloak Operator CI",
  "status" : "completed",
  "conclusion" : "success",
  "event" : "push",
  "path" : ".github/workflows/operator-ci.yml",
  "repository" : {
    "full_name" : "keycloak/keycloak"
  },
  "head_branch" : "release/24.0",
  "created_at" : "2024-06-18T13:33:06Z",
  "run_attempt" : 1
}, {
  "id" : 9566044025,
  "name" : "CodeQL",
  "status" : "completed",
  "conclusion" : "success",
  "event" : "push",
  "path" : ".github/workflows/codeql-analysis.yml",
  "repository" : {
    "full_name" : "keycloak/keycloak"
  },
  "head_branch" : "release/24.0",
  "created_at" : "2024-06-18T13:33:06Z",
  "run_attempt" : 1
}, {
  "id" : 9566037584,
  "name" : "Keycloak Guides",
  "status" : "completed",
  "conclusion" : "success",
  "event" : "push",
  "path" : ".github/workflows/guides.yml",
  "repository" : {
    "full_name" : "keycloak/keycloak"
  },
  "head_branch" : "release/25.0",
  "created_at" : "2024-06-18T13:32:42Z",
  "run_attempt" : 1
}, {
  "id" : 9566037614,
  "name" : "Keycloak JavaScript CI",
  "status" : "completed",
  "conclusion" : "failure",
  "event" : "push",
  "path" : ".github/workflows/js-ci.yml",
  "repository" : {
    "full_name" : "keycloak/keycloak"
  },
  "head_branch" : "release/25.0",
  "created_at" : "2024-06-18T13:32:42Z",
  "run_attempt" : 1
}, {
  "id" : 9566037549,
  "name" : "Keycloak Documentation",
  "status" : "completed",
  "conclusion" : "success",
  "event" : "push",
  "path" : ".github/workflows/documentation.yml",
  "repository" : {
    "full_name" : "keycloak/keycloak"
  },
  "head_branch" : "release/25.0",
  "created_at" : "2024-06-18T13:32:42Z",
  "run_attempt" : 1
}, {
  "id" : 9566037593,
  "name" : "Keycloak CI",
  "status" : "completed",
  "conclusion" : "failure",
  "event" : "push",
  "path" : ".github/workflows/ci.yml",
  "repository" : {
    "full_name" : "keycloak/keycloak"
  },
  "head_branch" : "release/25.0",
  "created_at" : "2024-06-18T13:32:42Z",
  "run_attempt" : 1
}, {
  "id" : 9566037575,
  "name" : "Keycloak Operator CI",
  "status" : "completed",
  "conclusion" : "success",
  "event" : "push",
  "path" : ".github/workflows/operator-ci.yml",
  "repository" : {
    "full_name" : "keycloak/keycloak"
  },
  "head_branch" : "release/25.0",
  "created_at" : "2024-06-18T13:32:42Z",
  "run_attempt" : 1
}, {
  "id" : 9566037548,
  "name" : "CodeQL",
  "status" : "completed",
  "conclusion" : "success",
  "event" : "push",
  "path" : ".github/workflows/codeql-analysis.yml",
  "repository" : {
    "full_name" : "keycloak/keycloak"
  },
  "head_branch" : "release/25.0",
  "created_at" : "2024-06-18T13:32:42Z",
  "run_attempt" : 1
}, {
  "id" : 9566028805,
  "name" : "Keycloak Guides",
  "status" : "completed",
  "conclusion" : "success",
  "event" : "push",
  "path" : ".github/workflows/guides.yml",
  "repository" : {
    "full_name" : "keycloak/keycloak"
  },
  "head_branch" : "release/22.0",
  "created_at" : "2024-06-18T13:32:13Z",
  "run_attempt" : 1
}, {
  "id" : 9566028806,
  "name" : "CodeQL",
  "status" : "completed",
  "conclusion" : "failure",
  "event" : "push",
  "path" : ".github/workflows/codeql-analysis.yml",
  "repository" : {
    "full_name" : "keycloak/keycloak"
  },
  "head_branch" : "release/22.0",
  "created_at" : "2024-06-18T13:32:13Z",
  "run_attempt" : 1
}, {
  "id" : 9566028815,
  "name" : "Keycloak Documentation",
  "status" : "completed",
  "conclusion" : "failure",
  "event" : "push",
  "path" : ".github/workflows/documentation.yml",
  "repository" : {
    "full_name" : "keycloak/keycloak"
  },
  "head_branch" : "release/22.0",
  "created_at" : "2024-06-18T13:32:13Z",
  "run_attempt" : 1
}, {
  "id" : 9566028799,
  "name" : "Keycloak JavaScript CI",
  "status" : "completed",
  "conclusion" : "success",
  "event" : "push",
  "path" : ".github/workflows/js-ci.yml",
  "repository" : {
    "full_name" : "keycloak/keycloak"
  },
  "head_branch" : "release/22.0",
  "created_at" : "2024-06-18T13:32:13Z",
  "run_attempt" : 1
}, {
  "id" : 9566028809,
  "name" : "Keycloak Operator CI",
  "status" : "completed",
  "conclusion" : "success",
  "event" : "push",
  "path" : ".github/workflows/operator-ci.yml",
  "repository" : {
    "full_name" : "keycloak/keycloak"
  },
  "head_branch" : "release/22.0",
  "created_at" : "2024-06-18T13:32:13Z",
  "run_attempt" : 1
}, {
  "id" : 9566028813,
  "name" : "Keycloak CI",
  "status" : "completed",
  "conclusion" : "success",
  "event" : "push",
  "path" : ".github/workflows/ci.yml",
  "repository" : {
    "full_name" : "keycloak/keycloak"
  },
  "head_branch" : "release/22.0",
  "created_at" : "2024-06-18T13:32:13Z",
  "run_attempt" : 1
}, {
  "id" : 9563880736,
  "name" : "Aurora Delete",
  "status" : "completed",
  "conclusion" : "success",
  "event" : "workflow_dispatch",
  "path" : ".github/workflows/aurora-delete.yml",
  "repository" : {
    "full_name" : "keycloak/keycloak"
  },
  "head_branch" : "feature/remote-cache",
  "created_at" : "2024-06-18T11:05:19Z",
  "run_attempt" : 1
}, {
  "id" : 9562690338,
  "name" : "Keycloak Operator CI",
  "status" : "completed",
  "conclusion" : "success",
  "event" : "push",
  "path" : ".github/workflows/operator-ci.yml",
  "repository" : {
    "full_name" : "keycloak/keycloak"
  },
  "head_branch" : "feature/remote-cache",
  "created_at" : "2024-06-18T09:38:12Z",
  "run_attempt" : 1
}, {
  "id" : 9562690323,
  "name" : "Keycloak CI",
  "status" : "completed",
  "conclusion" : "success",
  "event" : "push",
  "path" : ".github/workflows/ci.yml",
  "repository" : {
    "full_name" : "keycloak/keycloak"
  },
  "head_branch" : "feature/remote-cache",
  "created_at" : "2024-06-18T09:38:12Z",
  "run_attempt" : 1
}, {
  "id" : 9562690329,
  "name" : "CodeQL",
  "status" : "completed",
  "conclusion" : "success",
  "event" : "push",
  "path" : ".github/workflows/codeql-analysis.yml",
  "repository" : {
    "full_name" : "keycloak/keycloak"
  },
  "head_branch" : "feature/remote-cache",
  "created_at" : "2024-06-18T09:38:12Z",
  "run_attempt" : 1
}, {
  "id" : 9562690336,
  "name" : "Keycloak JavaScript CI",
  "status" : "completed",
  "conclusion" : "success",
  "event" : "push",
  "path" : ".github/workflows/js-ci.yml",
  "repository" : {
    "full_name" : "keycloak/keycloak"
  },
  "head_branch" : "feature/remote-cache",
  "created_at" : "2024-06-18T09:38:12Z",
  "run_attempt" : 1
}, {
  "id" : 9562690324,
  "name" : "Keycloak Documentation",
  "status" : "completed",
  "conclusion" : "success",
  "event" : "push",
  "path" : ".github/workflows/documentation.yml",
  "repository" : {
    "full_name" : "keycloak/keycloak"
  },
  "head_branch" : "feature/remote-cache",
  "created_at" : "2024-06-18T09:38:12Z",
  "run_attempt" : 1
}, {
  "id" : 9562690334,
  "name" : "Keycloak Guides",
  "status" : "completed",
  "conclusion" : "success",
  "event" : "push",
  "path" : ".github/workflows/guides.yml",
  "repository" : {
    "full_name" : "keycloak/keycloak"
  },
  "head_branch" : "feature/remote-cache",
  "created_at" : "2024-06-18T09:38:12Z",
  "run_attempt" : 1
}, {
  "id" : 9574352841,
  "name" : "Release Nightly",
  "status" : "completed",
  "conclusion" : "success",
  "event" : "schedule",
  "path" : ".github/workflows/release-nightly.yml",
  "repository" : {
    "full_name" : "keycloak-rel/keycloak-rel"
  },
  "head_branch" : "main",
  "created_at" : "2024-06-19T00:55:49Z",
  "run_attempt" : 1
} ]