[ {
  "id" : 20256272657,
  "name" : "Keycloak Operator CI",
  "status" : "completed",
  "conclusion" : "success",
  "event" : "workflow_dispatch",
  "path" : ".github/workflows/operator-ci.yml",
  "repository" : {
    "full_name" : "keycloak/keycloak"
  },
  "head_branch" : "main",
  "created_at" : "2025-12-16T04:14:24Z",
  "run_attempt" : 1
}, {
  "id" : 20256269766,
  "name" : "Keycloak Documentation",
  "status" : "completed",
  "conclusion" : "success",
  "event" : "workflow_dispatch",
  "path" : ".github/workflows/documentation.yml",
  "repository" : {
    "full_name" : "keycloak/keycloak"
  },
  "head_branch" : "main",
  "created_at" : "2025-12-16T04:14:15Z",
  "run_attempt" : 1
}, {
  "id" : 20256269034,
  "name" : "Trivy",
  "status" : "completed",
  "conclusion" : "success",
  "event" : "workflow_dispatch",
  "path" : ".github/workflows/trivy-analysis.yml",
  "repository" : {
    "full_name" : "keycloak/keycloak"
  },
  "head_branch" : "main",
  "created_at" : "2025-12-16T04:14:13Z",
  "run_attempt" : 1
}, {
  "id" : 20256269180,
  "name" : "Snyk",
  "status" : "completed",
  "conclusion" : "success",
  "event" : "workflow_dispatch",
  "path" : ".github/workflows/snyk-analysis.yml",
  "repository" : {
    "full_name" : "keycloak/keycloak"
  },
  "head_branch" : "main",
  "created_at" : "2025-12-16T04:14:13Z",
  "run_attempt" : 1
}, {
  "id" : 20256269222,
  "name" : "Snyk",
  "status" : "completed",
  "conclusion" : "success",
  "event" : "workflow_dispatch",
  "path" : ".github/workflows/snyk-analysis.yml",
  "repository" : {
    "full_name" : "keycloak/keycloak"
  },
  "head_branch" : "release/26.4",
  "created_at" : "2025-12-16T04:14:13Z",
  "run_attempt" : 1
}, {
  "id" : 20256269095,
  "name" : "CodeQL",
  "status" : "completed",
  "conclusion" : "success",
  "event" : "workflow_dispatch",
  "path" : ".github/workflows/codeql-analysis.yml",
  "repository" : {
    "full_name" : "keycloak/keycloak"
  },
  "head_branch" : "main",
  "created_at" : "2025-12-16T04:14:13Z",
  "run_attempt" : 1
}, {
  "id" : 20256269188,
  "name" : "Keycloak JavaScript CI",
  "status" : "completed",
  "conclusion" : "failure",
  "event" : "workflow_dispatch",
  "path" : ".github/workflows/js-ci.yml",
  "repository" : {
    "full_name" : "keycloak/keycloak"
  },
  "head_branch" : "main",
  "created_at" : "2025-12-16T04:14:13Z",
  "run_attempt" : 1
}, {
  "id" : 20256265898,
  "name" : "Scheduled nightly workflows",
  "status" : "completed",
  "conclusion" : "success",
  "event" : "schedule",
  "path" : ".github/workflows/schedule-nightly.yml",
  "repository" : {
    "full_name" : "keycloak/keycloak"
  },
  "head_branch" : "main",
  "created_at" : "2025-12-16T04:14:01Z",
  "run_attempt" : 1
}, {
  "id" : 20252274138,
  "name" : "Weblate Sync",
  "status" : "completed",
  "conclusion" : "success",
  "event" : "schedule",
  "path" : ".github/workflows/weblate.yml",
  "repository" : {
    "full_name" : "keycloak/keycloak"
  },
  "head_branch" : "main",
  "created_at" : "2025-12-16T00:31:33Z",
  "run_attempt" : 1
}, {
  "id" : 20252010536,
  "name" : "Aurora Delete",
  "status" : "completed",
  "conclusion" : "success",
  "event" : "workflow_dispatch",
  "path" : ".github/workflows/aurora-delete.yml",
  "repository" : {
    "full_name" : "keycloak/keycloak"
  },
  "head_branch" : "quarkus-next",
  "created_at" : "2025-12-16T00:19:06Z",
  "run_attempt" : 1
}, {
  "id" : 20251988705,
  "name" : "Keycloak CI",
  "status" : "completed",
  "conclusion" : "failure",
  "event" : "workflow_dispatch",
  "path" : ".github/workflows/ci.yml",
  "repository" : {
    "full_name" : "keycloak/keycloak"
  },
  "head_branch" : "quarkus-next",
  "created_at" : "2025-12-16T00:18:06Z",
  "run_attempt" : 1
}, {
  "id" : 20251988354,
  "name" : "Keycloak Operator CI",
  "status" : "completed",
  "conclusion" : "failure",
  "event" : "workflow_dispatch",
  "path" : ".github/workflows/operator-ci.yml",
  "repository" : {
    "full_name" : "keycloak/keycloak"
  },
  "head_branch" : "quarkus-next",
  "created_at" : "2025-12-16T00:18:05Z",
  "run_attempt" : 1
}, {
  "id" : 20251901929,
  "name" : "Quarkus Next",
  "status" : "completed",
  "conclusion" : "success",
  "event" : "schedule",
  "path" : ".github/workflows/quarkus-next.yml",
  "repository" : {
    "full_name" : "keycloak/keycloak"
  },
  "head_branch" : "main",
  "created_at" : "2025-12-16T00:13:52Z",
  "run_attempt" : 1
}, {
  "id" : 20221366214,
  "name" : "Aurora Delete",
  "status" : "completed",
  "conclusion" : "success",
  "event" : "workflow_dispatch",
  "path" : ".github/workflows/aurora-delete.yml",
  "repository" : {
    "full_name" : "keycloak/keycloak"
  },
  "head_branch" : "main",
  "created_at" : "2025-12-15T05:18:32Z",
  "run_attempt" : 1
}, {
  "id" : 20220352344,
  "name" : "Keycloak CI",
  "status" : "completed",
  "conclusion" : "success",
  "event" : "workflow_dispatch",
  "path" : ".github/workflows/ci.yml",
  "repository" : {
    "full_name" : "keycloak/keycloak"
  },
  "head_branch" : "main",
  "created_at" : "2025-12-15T04:19:12Z",
  "run_attempt" : 1
}, {
  "id" : 20256214436,
  "name" : "Keycloak Integration CI Nightly",
  "status" : "completed",
  "conclusion" : "success",
  "event" : "workflow_dispatch",
  "path" : ".github/workflows/nightly-ci.yml",
  "repository" : {
    "full_name" : "keycloak/keycloak-quickstarts"
  },
  "head_branch" : "main",
  "created_at" : "2025-12-16T04:11:16Z",
  "run_attempt" : 1
}, {
  "id" : 20256214286,
  "name" : "Keycloak Integration CI",
  "status" : "completed",
  "conclusion" : "success",
  "event" : "workflow_dispatch",
  "path" : ".github/workflows/ci.yml",
  "repository" : {
    "full_name" : "keycloak/keycloak-quickstarts"
  },
  "head_branch" : "main",
  "created_at" : "2025-12-16T04:11:15Z",
  "run_attempt" : 1
}, {
  "id" : 20256212584,
  "name" : "Scheduled workflows",
  "status" : "completed",
  "conclusion" : "success",
  "event" : "schedule",
  "path" : ".github/workflows/schedule.yml",
  "repository" : {
    "full_name" : "keycloak/keycloak-quickstarts"
  },
  "head_branch" : "main",
  "created_at" : "2025-12-16T04:11:10Z",
  "run_attempt" : 1
}, {
  "id" : 20253209561,
  "name" : "Release Nightly",
  "status" : "completed",
  "conclusion" : "success",
  "event" : "schedule",
  "path" : ".github/workflows/release-nightly.yml",
  "repository" : {
    "full_name" : "keycloak-rel/keycloak-rel"
  },
  "head_branch" : "main",
  "created_at" : "2025-12-16T01:20:57Z",
  "run_attempt" : 1
} ]