[ {
  "id" : 20611930268,
  "name" : "Aurora Delete",
  "status" : "completed",
  "conclusion" : "success",
  "event" : "workflow_dispatch",
  "path" : ".github/workflows/aurora-delete.yml",
  "repository" : {
    "full_name" : "keycloak/keycloak"
  },
  "head_branch" : "main",
  "created_at" : "2025-12-31T04:18:35Z",
  "run_attempt" : 1
}, {
  "id" : 20611907522,
  "name" : "Keycloak Documentation",
  "status" : "completed",
  "conclusion" : "success",
  "event" : "workflow_dispatch",
  "path" : ".github/workflows/documentation.yml",
  "repository" : {
    "full_name" : "keycloak/keycloak"
  },
  "head_branch" : "main",
  "created_at" : "2025-12-31T04:16:59Z",
  "run_attempt" : 1
}, {
  "id" : 20611906697,
  "name" : "CodeQL",
  "status" : "completed",
  "conclusion" : "success",
  "event" : "workflow_dispatch",
  "path" : ".github/workflows/codeql-analysis.yml",
  "repository" : {
    "full_name" : "keycloak/keycloak"
  },
  "head_branch" : "main",
  "created_at" : "2025-12-31T04:16:56Z",
  "run_attempt" : 1
}, {
  "id" : 20611906660,
  "name" : "Snyk",
  "status" : "completed",
  "conclusion" : "success",
  "event" : "workflow_dispatch",
  "path" : ".github/workflows/snyk-analysis.yml",
  "repository" : {
    "full_name" : "keycloak/keycloak"
  },
  "head_branch" : "main",
  "created_at" : "2025-12-31T04:16:56Z",
  "run_attempt" : 1
}, {
  "id" : 20611906731,
  "name" : "Keycloak JavaScript CI",
  "status" : "completed",
  "conclusion" : "success",
  "event" : "workflow_dispatch",
  "path" : ".github/workflows/js-ci.yml",
  "repository" : {
    "full_name" : "keycloak/keycloak"
  },
  "head_branch" : "main",
  "created_at" : "2025-12-31T04:16:56Z",
  "run_attempt" : 1
}, {
  "id" : 20611906695,
  "name" : "Keycloak Operator CI",
  "status" : "completed",
  "conclusion" : "success",
  "event" : "workflow_dispatch",
  "path" : ".github/workflows/operator-ci.yml",
  "repository" : {
    "full_name" : "keycloak/keycloak"
  },
  "head_branch" : "main",
  "created_at" : "2025-12-31T04:16:56Z",
  "run_attempt" : 1
}, {
  "id" : 20611906507,
  "name" : "Trivy",
  "status" : "completed",
  "conclusion" : "success",
  "event" : "workflow_dispatch",
  "path" : ".github/workflows/trivy-analysis.yml",
  "repository" : {
    "full_name" : "keycloak/keycloak"
  },
  "head_branch" : "main",
  "created_at" : "2025-12-31T04:16:55Z",
  "run_attempt" : 1
}, {
  "id" : 20611906543,
  "name" : "Snyk",
  "status" : "completed",
  "conclusion" : "success",
  "event" : "workflow_dispatch",
  "path" : ".github/workflows/snyk-analysis.yml",
  "repository" : {
    "full_name" : "keycloak/keycloak"
  },
  "head_branch" : "release/26.4",
  "created_at" : "2025-12-31T04:16:55Z",
  "run_attempt" : 1
}, {
  "id" : 20611902160,
  "name" : "Scheduled nightly workflows",
  "status" : "completed",
  "conclusion" : "success",
  "event" : "schedule",
  "path" : ".github/workflows/schedule-nightly.yml",
  "repository" : {
    "full_name" : "keycloak/keycloak"
  },
  "head_branch" : "main",
  "created_at" : "2025-12-31T04:16:37Z",
  "run_attempt" : 1
}, {
  "id" : 20609635335,
  "name" : "Aurora Delete",
  "status" : "completed",
  "conclusion" : "success",
  "event" : "workflow_dispatch",
  "path" : ".github/workflows/aurora-delete.yml",
  "repository" : {
    "full_name" : "keycloak/keycloak"
  },
  "head_branch" : "quarkus-next",
  "created_at" : "2025-12-31T01:17:48Z",
  "run_attempt" : 1
}, {
  "id" : 20609039589,
  "name" : "Weblate Sync",
  "status" : "completed",
  "conclusion" : "success",
  "event" : "schedule",
  "path" : ".github/workflows/weblate.yml",
  "repository" : {
    "full_name" : "keycloak/keycloak"
  },
  "head_branch" : "main",
  "created_at" : "2025-12-31T00:32:35Z",
  "run_attempt" : 1
}, {
  "id" : 20608843806,
  "name" : "Keycloak CI",
  "status" : "completed",
  "conclusion" : "success",
  "event" : "workflow_dispatch",
  "path" : ".github/workflows/ci.yml",
  "repository" : {
    "full_name" : "keycloak/keycloak"
  },
  "head_branch" : "quarkus-next",
  "created_at" : "2025-12-31T00:19:00Z",
  "run_attempt" : 1
}, {
  "id" : 20608843344,
  "name" : "Keycloak Operator CI",
  "status" : "completed",
  "conclusion" : "success",
  "event" : "workflow_dispatch",
  "path" : ".github/workflows/operator-ci.yml",
  "repository" : {
    "full_name" : "keycloak/keycloak"
  },
  "head_branch" : "quarkus-next",
  "created_at" : "2025-12-31T00:18:58Z",
  "run_attempt" : 1
}, {
  "id" : 20608777617,
  "name" : "Quarkus Next",
  "status" : "completed",
  "conclusion" : "success",
  "event" : "schedule",
  "path" : ".github/workflows/quarkus-next.yml",
  "repository" : {
    "full_name" : "keycloak/keycloak"
  },
  "head_branch" : "main",
  "created_at" : "2025-12-31T00:14:26Z",
  "run_attempt" : 1
}, {
  "id" : 20588738520,
  "name" : "Keycloak CI",
  "status" : "completed",
  "conclusion" : "success",
  "event" : "workflow_dispatch",
  "path" : ".github/workflows/ci.yml",
  "repository" : {
    "full_name" : "keycloak/keycloak"
  },
  "head_branch" : "main",
  "created_at" : "2025-12-30T04:17:30Z",
  "run_attempt" : 1
}, {
  "id" : 20611864182,
  "name" : "Keycloak Integration CI",
  "status" : "completed",
  "conclusion" : "failure",
  "event" : "workflow_dispatch",
  "path" : ".github/workflows/ci.yml",
  "repository" : {
    "full_name" : "keycloak/keycloak-quickstarts"
  },
  "head_branch" : "main",
  "created_at" : "2025-12-31T04:13:54Z",
  "run_attempt" : 1
}, {
  "id" : 20611863534,
  "name" : "Keycloak Integration CI Nightly",
  "status" : "completed",
  "conclusion" : "failure",
  "event" : "workflow_dispatch",
  "path" : ".github/workflows/nightly-ci.yml",
  "repository" : {
    "full_name" : "keycloak/keycloak-quickstarts"
  },
  "head_branch" : "main",
  "created_at" : "2025-12-31T04:13:51Z",
  "run_attempt" : 1
}, {
  "id" : 20611862211,
  "name" : "Scheduled workflows",
  "status" : "completed",
  "conclusion" : "success",
  "event" : "schedule",
  "path" : ".github/workflows/schedule.yml",
  "repository" : {
    "full_name" : "keycloak/keycloak-quickstarts"
  },
  "head_branch" : "main",
  "created_at" : "2025-12-31T04:13:45Z",
  "run_attempt" : 1
}, {
  "id" : 20609688307,
  "name" : "Release Nightly",
  "status" : "completed",
  "conclusion" : "failure",
  "event" : "schedule",
  "path" : ".github/workflows/release-nightly.yml",
  "repository" : {
    "full_name" : "keycloak-rel/keycloak-rel"
  },
  "head_branch" : "main",
  "created_at" : "2025-12-31T01:21:54Z",
  "run_attempt" : 1
} ]