[ {
  "id" : 9232163358,
  "name" : "Aurora Delete",
  "status" : "completed",
  "conclusion" : "success",
  "event" : "workflow_dispatch",
  "path" : ".github/workflows/aurora-delete.yml",
  "repository" : {
    "full_name" : "keycloak/keycloak"
  },
  "head_branch" : "main",
  "created_at" : "2024-05-25T02:13:26Z",
  "run_attempt" : 1
}, {
  "id" : 9232117478,
  "name" : "Aurora Delete",
  "status" : "completed",
  "conclusion" : "success",
  "event" : "workflow_dispatch",
  "path" : ".github/workflows/aurora-delete.yml",
  "repository" : {
    "full_name" : "keycloak/keycloak"
  },
  "head_branch" : "quarkus-next",
  "created_at" : "2024-05-25T02:06:14Z",
  "run_attempt" : 1
}, {
  "id" : 9231325429,
  "name" : "Keycloak Operator CI",
  "status" : "completed",
  "conclusion" : "success",
  "event" : "workflow_dispatch",
  "path" : ".github/workflows/operator-ci.yml",
  "repository" : {
    "full_name" : "keycloak/keycloak"
  },
  "head_branch" : "main",
  "created_at" : "2024-05-25T00:14:14Z",
  "run_attempt" : 1
}, {
  "id" : 9231325416,
  "name" : "Trivy",
  "status" : "completed",
  "conclusion" : "success",
  "event" : "workflow_dispatch",
  "path" : ".github/workflows/trivy-analysis.yml",
  "repository" : {
    "full_name" : "keycloak/keycloak"
  },
  "head_branch" : "main",
  "created_at" : "2024-05-25T00:14:14Z",
  "run_attempt" : 1
}, {
  "id" : 9231325424,
  "name" : "Keycloak Documentation",
  "status" : "completed",
  "conclusion" : "success",
  "event" : "workflow_dispatch",
  "path" : ".github/workflows/documentation.yml",
  "repository" : {
    "full_name" : "keycloak/keycloak"
  },
  "head_branch" : "main",
  "created_at" : "2024-05-25T00:14:14Z",
  "run_attempt" : 1
}, {
  "id" : 9231325130,
  "name" : "Keycloak JavaScript CI",
  "status" : "completed",
  "conclusion" : "success",
  "event" : "workflow_dispatch",
  "path" : ".github/workflows/js-ci.yml",
  "repository" : {
    "full_name" : "keycloak/keycloak"
  },
  "head_branch" : "main",
  "created_at" : "2024-05-25T00:14:12Z",
  "run_attempt" : 1
}, {
  "id" : 9231325152,
  "name" : "Keycloak CI",
  "status" : "completed",
  "conclusion" : "success",
  "event" : "workflow_dispatch",
  "path" : ".github/workflows/ci.yml",
  "repository" : {
    "full_name" : "keycloak/keycloak"
  },
  "head_branch" : "main",
  "created_at" : "2024-05-25T00:14:12Z",
  "run_attempt" : 1
}, {
  "id" : 9231322481,
  "name" : "Scheduled nightly workflows",
  "status" : "completed",
  "conclusion" : "failure",
  "event" : "schedule",
  "path" : ".github/workflows/schedule-nightly.yml",
  "repository" : {
    "full_name" : "keycloak/keycloak"
  },
  "head_branch" : "main",
  "created_at" : "2024-05-25T00:13:54Z",
  "run_attempt" : 1
}, {
  "id" : 9231296372,
  "name" : "Keycloak Operator CI",
  "status" : "completed",
  "conclusion" : "success",
  "event" : "workflow_dispatch",
  "path" : ".github/workflows/operator-ci.yml",
  "repository" : {
    "full_name" : "keycloak/keycloak"
  },
  "head_branch" : "quarkus-next",
  "created_at" : "2024-05-25T00:10:43Z",
  "run_attempt" : 1
}, {
  "id" : 9231296019,
  "name" : "Keycloak CI",
  "status" : "completed",
  "conclusion" : "failure",
  "event" : "workflow_dispatch",
  "path" : ".github/workflows/ci.yml",
  "repository" : {
    "full_name" : "keycloak/keycloak"
  },
  "head_branch" : "quarkus-next",
  "created_at" : "2024-05-25T00:10:41Z",
  "run_attempt" : 1
}, {
  "id" : 9231278175,
  "name" : "Quarkus Next",
  "status" : "completed",
  "conclusion" : "success",
  "event" : "schedule",
  "path" : ".github/workflows/quarkus-next.yml",
  "repository" : {
    "full_name" : "keycloak/keycloak"
  },
  "head_branch" : "main",
  "created_at" : "2024-05-25T00:08:31Z",
  "run_attempt" : 1
}, {
  "id" : 9206592268,
  "name" : "Keycloak Operator CI",
  "status" : "completed",
  "conclusion" : "success",
  "event" : "push",
  "path" : ".github/workflows/operator-ci.yml",
  "repository" : {
    "full_name" : "keycloak/keycloak"
  },
  "head_branch" : "release/24.0",
  "created_at" : "2024-05-23T10:42:28Z",
  "run_attempt" : 1
}, {
  "id" : 9206592273,
  "name" : "Keycloak Documentation",
  "status" : "completed",
  "conclusion" : "success",
  "event" : "push",
  "path" : ".github/workflows/documentation.yml",
  "repository" : {
    "full_name" : "keycloak/keycloak"
  },
  "head_branch" : "release/24.0",
  "created_at" : "2024-05-23T10:42:28Z",
  "run_attempt" : 1
}, {
  "id" : 9206592272,
  "name" : "Keycloak JavaScript CI",
  "status" : "completed",
  "conclusion" : "success",
  "event" : "push",
  "path" : ".github/workflows/js-ci.yml",
  "repository" : {
    "full_name" : "keycloak/keycloak"
  },
  "head_branch" : "release/24.0",
  "created_at" : "2024-05-23T10:42:28Z",
  "run_attempt" : 1
}, {
  "id" : 9206592269,
  "name" : "CodeQL",
  "status" : "completed",
  "conclusion" : "success",
  "event" : "push",
  "path" : ".github/workflows/codeql-analysis.yml",
  "repository" : {
    "full_name" : "keycloak/keycloak"
  },
  "head_branch" : "release/24.0",
  "created_at" : "2024-05-23T10:42:28Z",
  "run_attempt" : 1
}, {
  "id" : 9206592271,
  "name" : "Keycloak CI",
  "status" : "completed",
  "conclusion" : "success",
  "event" : "push",
  "path" : ".github/workflows/ci.yml",
  "repository" : {
    "full_name" : "keycloak/keycloak"
  },
  "head_branch" : "release/24.0",
  "created_at" : "2024-05-23T10:42:28Z",
  "run_attempt" : 1
}, {
  "id" : 9206592270,
  "name" : "Keycloak Guides",
  "status" : "completed",
  "conclusion" : "success",
  "event" : "push",
  "path" : ".github/workflows/guides.yml",
  "repository" : {
    "full_name" : "keycloak/keycloak"
  },
  "head_branch" : "release/24.0",
  "created_at" : "2024-05-23T10:42:28Z",
  "run_attempt" : 1
}, {
  "id" : 9206416558,
  "name" : "Keycloak Operator CI",
  "status" : "completed",
  "conclusion" : "success",
  "event" : "push",
  "path" : ".github/workflows/operator-ci.yml",
  "repository" : {
    "full_name" : "keycloak/keycloak"
  },
  "head_branch" : "feature/testsuite-refactor",
  "created_at" : "2024-05-23T10:28:55Z",
  "run_attempt" : 1
}, {
  "id" : 9206416577,
  "name" : "Keycloak Guides",
  "status" : "completed",
  "conclusion" : "success",
  "event" : "push",
  "path" : ".github/workflows/guides.yml",
  "repository" : {
    "full_name" : "keycloak/keycloak"
  },
  "head_branch" : "feature/testsuite-refactor",
  "created_at" : "2024-05-23T10:28:55Z",
  "run_attempt" : 1
}, {
  "id" : 9206416587,
  "name" : "Keycloak CI",
  "status" : "completed",
  "conclusion" : "success",
  "event" : "push",
  "path" : ".github/workflows/ci.yml",
  "repository" : {
    "full_name" : "keycloak/keycloak"
  },
  "head_branch" : "feature/testsuite-refactor",
  "created_at" : "2024-05-23T10:28:55Z",
  "run_attempt" : 1
}, {
  "id" : 9206416568,
  "name" : "CodeQL",
  "status" : "completed",
  "conclusion" : "success",
  "event" : "push",
  "path" : ".github/workflows/codeql-analysis.yml",
  "repository" : {
    "full_name" : "keycloak/keycloak"
  },
  "head_branch" : "feature/testsuite-refactor",
  "created_at" : "2024-05-23T10:28:55Z",
  "run_attempt" : 1
}, {
  "id" : 9206416562,
  "name" : "Keycloak JavaScript CI",
  "status" : "completed",
  "conclusion" : "failure",
  "event" : "push",
  "path" : ".github/workflows/js-ci.yml",
  "repository" : {
    "full_name" : "keycloak/keycloak"
  },
  "head_branch" : "feature/testsuite-refactor",
  "created_at" : "2024-05-23T10:28:55Z",
  "run_attempt" : 1
}, {
  "id" : 9206416563,
  "name" : "Keycloak Documentation",
  "status" : "completed",
  "conclusion" : "success",
  "event" : "push",
  "path" : ".github/workflows/documentation.yml",
  "repository" : {
    "full_name" : "keycloak/keycloak"
  },
  "head_branch" : "feature/testsuite-refactor",
  "created_at" : "2024-05-23T10:28:55Z",
  "run_attempt" : 1
}, {
  "id" : 9200223217,
  "name" : "Snyk",
  "status" : "completed",
  "conclusion" : "success",
  "event" : "workflow_dispatch",
  "path" : ".github/workflows/snyk-analysis.yml",
  "repository" : {
    "full_name" : "keycloak/keycloak"
  },
  "head_branch" : "main",
  "created_at" : "2024-05-23T00:25:48Z",
  "run_attempt" : 1
}, {
  "id" : 9200220024,
  "name" : "Snyk",
  "status" : "completed",
  "conclusion" : "success",
  "event" : "workflow_dispatch",
  "path" : ".github/workflows/snyk-analysis.yml",
  "repository" : {
    "full_name" : "keycloak/keycloak"
  },
  "head_branch" : "release/24.0",
  "created_at" : "2024-05-23T00:25:28Z",
  "run_attempt" : 1
}, {
  "id" : 9198106763,
  "name" : "Keycloak CI",
  "status" : "completed",
  "conclusion" : "success",
  "event" : "push",
  "path" : ".github/workflows/ci.yml",
  "repository" : {
    "full_name" : "keycloak/keycloak"
  },
  "head_branch" : "issue-29494-backport24",
  "created_at" : "2024-05-22T20:40:04Z",
  "run_attempt" : 1
}, {
  "id" : 9198106761,
  "name" : "Keycloak Guides",
  "status" : "completed",
  "conclusion" : "success",
  "event" : "push",
  "path" : ".github/workflows/guides.yml",
  "repository" : {
    "full_name" : "keycloak/keycloak"
  },
  "head_branch" : "issue-29494-backport24",
  "created_at" : "2024-05-22T20:40:04Z",
  "run_attempt" : 1
}, {
  "id" : 9198106764,
  "name" : "Keycloak Documentation",
  "status" : "completed",
  "conclusion" : "success",
  "event" : "push",
  "path" : ".github/workflows/documentation.yml",
  "repository" : {
    "full_name" : "keycloak/keycloak"
  },
  "head_branch" : "issue-29494-backport24",
  "created_at" : "2024-05-22T20:40:04Z",
  "run_attempt" : 1
}, {
  "id" : 9198106759,
  "name" : "CodeQL",
  "status" : "completed",
  "conclusion" : "failure",
  "event" : "push",
  "path" : ".github/workflows/codeql-analysis.yml",
  "repository" : {
    "full_name" : "keycloak/keycloak"
  },
  "head_branch" : "issue-29494-backport24",
  "created_at" : "2024-05-22T20:40:04Z",
  "run_attempt" : 1
}, {
  "id" : 9198106768,
  "name" : "Keycloak Operator CI",
  "status" : "completed",
  "conclusion" : "success",
  "event" : "push",
  "path" : ".github/workflows/operator-ci.yml",
  "repository" : {
    "full_name" : "keycloak/keycloak"
  },
  "head_branch" : "issue-29494-backport24",
  "created_at" : "2024-05-22T20:40:04Z",
  "run_attempt" : 1
}, {
  "id" : 9198106776,
  "name" : "Keycloak JavaScript CI",
  "status" : "completed",
  "conclusion" : "success",
  "event" : "push",
  "path" : ".github/workflows/js-ci.yml",
  "repository" : {
    "full_name" : "keycloak/keycloak"
  },
  "head_branch" : "issue-29494-backport24",
  "created_at" : "2024-05-22T20:40:04Z",
  "run_attempt" : 1
}, {
  "id" : 9231618756,
  "name" : "Release Nightly",
  "status" : "completed",
  "conclusion" : "success",
  "event" : "schedule",
  "path" : ".github/workflows/release-nightly.yml",
  "repository" : {
    "full_name" : "keycloak-rel/keycloak-rel"
  },
  "head_branch" : "main",
  "created_at" : "2024-05-25T00:52:17Z",
  "run_attempt" : 1
} ]